{
    "author": "naazimsnh02",
    "github_id": "naazimsnh02",
    "val_bpb": null,
    "date": "2026-03-25",
    "summary": "Depth Recurrence (layers 4,5) + LoRA TTT (rank 8) + Parallel Muon on PR #549 stack",
    "architecture": "11L 512d 8H/4KV GQA, 3x MLP LeakyReLU(0.5)², depth recurrence layers 4+5, XSA4, PartialRoPE 16/64, LN Scale, BigramHash(2048), SmearGate, VE128, EMA+SWA, Int6 GPTQ-lite + lzma",
    "training_time_seconds": null,
    "artifact_bytes": null,
    "num_seeds": 1,
    "gpu": "8xH100 SXM"
}
