{
  "name": "11L XSA + LeakyReLU(0.5)² + Legal Score-First TTT (ADIITJ)",
  "author": "Atharva Date",
  "github_id": "ADIITJ",
  "date": "2026-03-23",
  "val_bpb": null,
  "val_bpb_seeds": null,
  "seeds": null,
  "status": "non_record_pending_validation",
  "blurb": "11-layer transformer with XSA (all layers), partial RoPE (16/64 dims), LN scale (1/sqrt(L+1)), VE128 (layers 9,10), LeakyReLU(0.5)² activation, BigramHash(2048), SWA, INT6+zstd-22. Legal score-first TTT at eval: sequential 32K-token chunks, score then adapt, all blocks unfrozen, SGD(lr=0.002, mom=0.9), 3 epochs/chunk, cosine LR. Attribution: PR #503 (EthanYangTW), PR #518 (sofiabod), PR #549 (abaybektursun).",
  "architecture": "11L_512dim_8h_4kv_XSA11_PartialRoPE16_LNScale_VE128_LeakyReLU",
  "num_layers": 11,
  "model_dim": 512,
  "num_heads": 8,
  "num_kv_heads": 4,
  "xsa_last_n": 11,
  "rope_dims": 16,
  "ln_scale": true,
  "ve_enabled": true,
  "ve_dim": 128,
  "ve_layers": "9,10",
  "bigram_vocab_size": 2048,
  "bigram_dim": 128,
  "quantization": "int6_per_row_zstd22",
  "ttt_mode": "legal_score_first_sequential",
  "ttt_epochs": 3,
  "ttt_lr": 0.002,
  "ttt_optimizer": "sgd",
  "ttt_freeze_blocks": 0,
  "ttt_chunk_tokens": 32768,
  "platform": "RunPod 8xH100 SXM"
}
