{
  "name": "PROTEUS+ — 11L INT6 + Cosine LoRA TTT (3ep, batch=64)",
  "author": "Atharva Date",
  "github_id": "ADIITJ",
  "date": "2026-03-23",
  "val_bpb": null,
  "val_bpb_seeds": null,
  "seeds": null,
  "status": "non_record_pending_validation",
  "blurb": "Builds on PROTEUS v7 (PR #512, MatoTeziTanka, 0.9512 bpb): 11L transformer, INT6 uniform quantization, depth-scaled residuals, OrthoInit, SWA, EMA. Key addition: cosine LR annealing for LoRA TTT evaluation (base_lr=0.008 → min_lr=1e-5 over 3 epochs, inspired by PR #517 cosine schedule). Also reduces ttt_min_doc_len from 1024→512 to adapt more documents. Zero artifact cost — LoRA weights initialized and discarded per document.",
  "base_attribution": "PROTEUS v7 architecture by MatoTeziTanka (PR #512). Cosine LR TTT schedule by lukacf (PR #517).",
  "ttt_lora_rank": 8,
  "ttt_lora_lr": 0.008,
  "ttt_lora_lr_min": 1e-5,
  "ttt_epochs": 3,
  "ttt_cosine_lr": true,
  "ttt_chunk_size": 256,
  "ttt_eval_seq_len": 1024,
  "ttt_batch_size": 64,
  "ttt_min_doc_len": 512,
  "num_layers": 11,
  "model_dim": 512,
  "mlp_hidden": 1536,
  "quantization": "INT6 uniform per-row",
  "compression": "zstd-22",
  "platform": "RunPod 8xH100 SXM"
}
