{
  "author": "mrdavtan",
  "github_id": "mrdavtan",
  "name": "11L XSA + EMA + TTT + Partial RoPE + LN Scale (val_bpb=1.1401)",
  "blurb": "11-layer transformer with XSA (last 4 layers), EMA weight averaging, Test-Time Training, U-Net skip connections, Partial RoPE (16/64 dims), LN Scale, SmearGate, BigramHash, and late absmax QAT. Includes corrected SmearGate interpolation and BigramHash XOR hashing.",
  "date": "2026-03-21",
  "val_loss": 1.9251,
  "val_bpb": 1.1401,
  "step_stop": 7100,
  "wallclock_seconds": 600.0,
  "eval_time_seconds": 398.3,
  "bytes_total": 16155425,
  "bytes_model_int8_zstd": 16069980,
  "bytes_code": 85445,
  "hardware": "8xH100 SXM (RunPod Parameter Golf template), PyTorch 2.9.1+cu128",
  "seed": 1337,
  "num_seeds": 1,
  "seed_results": {
    "1337": 1.1401
  },
  "track": "track_10min_16mb",
  "model": {
    "num_layers": 11,
    "model_dim": 512,
    "num_heads": 8,
    "num_kv_heads": 4,
    "mlp_mult": 3,
    "vocab_size": 1024,
    "tie_embeddings": true,
    "total_params": 26829913
  },
  "techniques": [
    "XSA (Exclusive Self Attention) on last 4 layers",
    "EMA (decay=0.997, float32 accumulation)",
    "TTT (3-epoch full-weight SGD, lr=0.002, freeze first 2 blocks)",
    "U-Net skip connections (encoder 5, decoder 6, learned weights)",
    "Partial RoPE (16/64 head dims)",
    "LN Scale (1/sqrt(layer_idx+1) on RMSNorm output)",
    "SmearGate (per-channel interpolation, torch.lerp)",
    "BigramHash (XOR hash, learned output scalar)",
    "OrthoInit on all large matrices",
    "Late QAT (absmax int6 STE, lr_scale < 0.1 trigger)",
    "Int6 per-row quantization + zstd-22",
    "FP16 tied embedding + late-K FP16 export",
    "Sliding window eval (stride=32)"
  ],
  "config": {
    "NUM_LAYERS": 11,
    "MODEL_DIM": 512,
    "NUM_HEADS": 8,
    "NUM_KV_HEADS": 4,
    "MLP_MULT": 3,
    "QUANT_BITS": 6,
    "USE_ZSTD": 1,
    "TIE_EMBEDDINGS": 1,
    "FP16_EMBED_EXPORT": 1,
    "TRAIN_SEQ_LEN": 2048,
    "EVAL_SEQ_LEN": 2048,
    "ROPE_BASE": 10000,
    "TRAIN_BATCH_TOKENS": 524288,
    "WARMDOWN_ITERS": 3000,
    "XSA_LAST_N": 4,
    "EMA_ENABLED": 1,
    "EMA_DECAY": 0.997,
    "TTT_ENABLED": 1,
    "TTT_LR": 0.002,
    "TTT_EPOCHS": 3,
    "TTT_FREEZE_BLOCKS": 2,
    "SMEAR_GATE": 1,
    "BIGRAM_HASH": 1,
    "ORTHO_INIT": 1,
    "UNET_SKIPS": 1,
    "ROPE_DIMS": 16,
    "LN_SCALE": 1,
    "MUON_MOMENTUM": 0.99,
    "GRAD_CLIP_NORM": 0.3,
    "MUON_WD": 0.04,
    "ADAM_WD": 0.04,
    "MATRIX_LR": 0.025,
    "SCALAR_LR": 0.025,
    "TIED_EMBED_LR": 0.035,
    "EVAL_STRIDE": 32,
    "DOC_ISOLATED_EVAL": 0,
    "QAT": 1
  }
}
