{
  "author": "",
  "github_id": "JUSTSUJAY",
  "name": "5L MLP4x + BigramHash + SmearGate + OrthoInit + SWA + QAT + Sliding Window (1xH100)",
  "blurb": "Non-record 1xH100 submission: 20+ experiments exploring width-vs-depth tradeoffs, discovering that 5-layer MLP4x (hidden=2048) significantly outperforms deeper narrower architectures. Combined with BigramHash(4096), SmearGate, orthogonal init, QAT (int8 STE), SWA (38 checkpoints), and sliding window eval (stride=64). Post-quant val_bpb 1.3380 with 10-minute training budget on 1xH100 80GB (14.5MB artifact). Autonomous AI-driven experimentation using autoresearch framework.",
  "date": "2026-03-26T00:00:00Z",
  "track": "non-record-16mb",
  "val_loss": null,
  "val_bpb": 1.337977,
  "pre_quant_val_loss": null,
  "pre_quant_val_bpb": 1.337463,
  "step_stop": 9353,
  "wallclock_seconds": 600,
  "eval_time_seconds": 227.3,
  "bytes_total": 14511799,
  "bytes_model_int8_zlib": null,
  "bytes_code": null,
  "gpu": "1xH100-80GB"
}
